entropython/__init__.py
entropython/libentropython.cpython-313t-x86_64-linux-gnu.so
entropython-1.2.0.dist-info/METADATA
entropython-1.2.0.dist-info/WHEEL
entropython-1.2.0.dist-info/top_level.txt
entropython-1.2.0.dist-info/RECORD
entropython-1.2.0.dist-info/licenses/LICENSE
