Metadata-Version: 2.4
Name: entropython
Version: 1.2.0
Summary: A Python module for efficient calculation of Shannon byte entropy based on Rust.
License: MIT License
Project-URL: Homepage, https://github.com/fkie-cad/entropython
Keywords: entropy
Requires-Python: >=3.8
License-File: LICENSE
Provides-Extra: dev
Requires-Dist: pytest>=8; extra == "dev"
Requires-Dist: twine~=5.1.1; extra == "dev"
Requires-Dist: build~=1.2.1; extra == "dev"
Dynamic: license-file
